{"url":"https:\/\/dev.vestrus.ru\/rest\/user.admin.json","info":{"url":"https:\/\/dev.vestrus.ru\/rest\/user.admin.json","content_type":"application\/json; charset=utf-8","http_code":200,"header_size":731,"request_size":255,"filetime":-1,"ssl_verify_result":0,"redirect_count":0,"total_time":0.40415900000000005,"namelookup_time":0.004128,"connect_time":0.004248,"pretransfer_time":0.012968,"size_upload":75,"size_download":225,"speed_download":556,"speed_upload":185,"download_content_length":225,"upload_content_length":75,"starttransfer_time":0.40413699999999997,"redirect_time":0,"redirect_url":"","primary_ip":"192.168.1.47","certinfo":[],"primary_port":443,"local_ip":"192.168.1.47","local_port":35694},"params":{"method":"user.admin","params":{"auth":"79ffa16700749454005843ea00000321000007e58e48ee2e61cd242a71a095d097bab8"}},"result":{"result":true,"time":{"start":1738666347.259176,"finish":1738666347.532002,"duration":0.2728259563446045,"processing":2.4080276489257812e-5,"date_start":"2025-02-04T13:52:27+03:00","date_finish":"2025-02-04T13:52:27+03:00"}}}