{"url":"https:\/\/gkyw.ru\/rest\/im.message.add.json","info":{"url":"https:\/\/gkyw.ru\/rest\/im.message.add.json","content_type":"application\/json; charset=utf-8","http_code":200,"header_size":747,"request_size":592,"filetime":-1,"ssl_verify_result":0,"redirect_count":0,"total_time":0.500543,"namelookup_time":0.00415,"connect_time":0.004258,"pretransfer_time":0.013410000000000033,"size_upload":414,"size_download":226,"speed_download":451,"speed_upload":827,"download_content_length":226,"upload_content_length":414,"starttransfer_time":0.500523,"redirect_time":0,"redirect_url":"","primary_ip":"192.168.0.81","certinfo":[],"primary_port":443,"local_ip":"192.168.0.81","local_port":55320},"params":{"method":"im.message.add","params":{"DIALOG_ID":"chat95037","MESSAGE":"\u0421\u043e\u0442\u0440\u0443\u0434\u043d\u0438\u043a [b]\u041b\u044e\u043b\u044c\u043a\u0438\u043d \u0421\u0435\u0440\u0433\u0435\u0439[\/b] 22.05.2024 \u0441\u043d\u044f\u043b \u0441 \u043a\u0430\u0440\u0442\u044b (0105) 15 001 \u0440\u0443\u0431.","SYSTEM":"N","ATTACH":"","URL_PREVIEW":"Y","KEYBOARD":"","MENU":"","auth":"c5a04c66005868f4005843ea000001e70000077986a16e8d0f4c6a15afe6d8f232ab35"}},"result":{"result":3897614,"time":{"start":1716295248.620331,"finish":1716295249.071534,"duration":0.4512028694152832,"processing":0.06378388404846191,"date_start":"2024-05-21T15:40:48+03:00","date_finish":"2024-05-21T15:40:49+03:00"}}}