{"url":"https:\/\/gkyw.ru\/rest\/batch.json","info":{"url":"https:\/\/gkyw.ru\/rest\/batch.json","content_type":"application\/json; charset=utf-8","http_code":200,"header_size":773,"request_size":193,"filetime":-1,"ssl_verify_result":0,"redirect_count":0,"total_time":1.357289,"namelookup_time":0.00414,"connect_time":0.004233,"pretransfer_time":0.013514,"size_upload":11216,"size_download":1537,"speed_download":1132,"speed_upload":8263,"download_content_length":1537,"upload_content_length":11216,"starttransfer_time":0.013711,"redirect_time":0,"redirect_url":"","primary_ip":"192.168.0.81","certinfo":[],"primary_port":443,"local_ip":"192.168.0.81","local_port":10358},"params":{"method":"batch","params":{"cmd":{"15":"lists.element.add?IBLOCK_TYPE_ID=lists\u0026IBLOCK_ID=28\u0026ELEMENT_CODE=778d62a2a735fe340507dd543733373e\u0026FIELDS%5BNAME%5D=757584\u0026FIELDS%5BPROPERTY_149%5D=757584\u0026FIELDS%5BPROPERTY_146%5D=2024-03-18\u0026FIELDS%5BPROPERTY_147%5D=10000000.00\u0026FIELDS%5BPROPERTY_150%5D=7730060164\u0026FIELDS%5BPROPERTY_151%5D=%D0%98%D0%9D%D0%9D+7730060164+%D0%9F%D0%A0%D0%98%D0%92%D0%9E%D0%9B%D0%96%D0%A1%D0%9A%D0%98%D0%99+%D0%A4%D0%98%D0%9B%D0%98%D0%90%D0%9B+%D0%9F%D0%90%D0%9E+%D0%A0%D0%9E%D0%A1%D0%91%D0%90%D0%9D%D0%9A\u0026FIELDS%5BPROPERTY_152%5D=8\u0026FIELDS%5BPROPERTY_153%5D=40702810524870001858\u0026FIELDS%5BPROPERTY_154%5D=%D0%9E%D0%9E%D0%9E+%22%D0%92%D0%AD%D0%A1%D0%A2%22%7E6+%D0%BF%D1%80%D0%B5%D0%B4%D0%BE%D1%81%D1%82%D0%B0%D0%B2%D0%BB%D0%B5%D0%BD%D0%B8%D0%B5+%D0%BA%D1%80%D0%B5%D0%B4%D0%B8%D1%82%D0%B0+%D0%94%D0%BE%D0%B3.MSW-R24-23-001054%2F04_18%2F03%2F2024\u0026FIELDS%5BPROPERTY_148%5D=10000000.00\u0026FIELDS%5BPROPERTY_160%5D=0\u0026FIELDS%5BPROPERTY_162%5D=25.03.2024\u0026FIELDS%5BPROPERTY_163%5D=60\u0026FIELDS%5BPROPERTY_166%5D=60\u0026FIELDS%5BPROPERTY_260%5D=CO_2393","18":"lists.element.add?IBLOCK_TYPE_ID=lists\u0026IBLOCK_ID=28\u0026ELEMENT_CODE=9c64d5ff9e3619ee75d25b497c70391a\u0026FIELDS%5BNAME%5D=170259\u0026FIELDS%5BPROPERTY_149%5D=170259\u0026FIELDS%5BPROPERTY_146%5D=2024-03-19\u0026FIELDS%5BPROPERTY_147%5D=300000.00\u0026FIELDS%5BPROPERTY_150%5D=7730060164\u0026FIELDS%5BPROPERTY_151%5D=%D0%98%D0%9D%D0%9D+7730060164+%D0%9F%D0%A0%D0%98%D0%92%D0%9E%D0%9B%D0%96%D0%A1%D0%9A%D0%98%D0%99+%D0%A4%D0%98%D0%9B%D0%98%D0%90%D0%9B+%D0%9F%D0%90%D0%9E+%D0%A0%D0%9E%D0%A1%D0%91%D0%90%D0%9D%D0%9A\u0026FIELDS%5BPROPERTY_152%5D=8\u0026FIELDS%5BPROPERTY_153%5D=40702810524870001858\u0026FIELDS%5BPROPERTY_154%5D=%D0%9E%D0%9E%D0%9E+%22%D0%92%D0%AD%D0%A1%D0%A2%22%7E6+%D0%BF%D1%80%D0%B5%D0%B4%D0%BE%D1%81%D1%82%D0%B0%D0%B2%D0%BB%D0%B5%D0%BD%D0%B8%D0%B5+%D0%BA%D1%80%D0%B5%D0%B4%D0%B8%D1%82%D0%B0+%D0%94%D0%BE%D0%B3.MSW-R24-23-001054%2F06_19%2F03%2F2024\u0026FIELDS%5BPROPERTY_148%5D=300000.00\u0026FIELDS%5BPROPERTY_160%5D=0\u0026FIELDS%5BPROPERTY_162%5D=25.03.2024\u0026FIELDS%5BPROPERTY_163%5D=60\u0026FIELDS%5BPROPERTY_166%5D=60\u0026FIELDS%5BPROPERTY_260%5D=CO_2393","19":"lists.element.add?IBLOCK_TYPE_ID=lists\u0026IBLOCK_ID=28\u0026ELEMENT_CODE=76822b7800db990a7403536ebb9fb0e5\u0026FIELDS%5BNAME%5D=136868\u0026FIELDS%5BPROPERTY_149%5D=136868\u0026FIELDS%5BPROPERTY_146%5D=2024-03-19\u0026FIELDS%5BPROPERTY_147%5D=3300000.00\u0026FIELDS%5BPROPERTY_150%5D=7730060164\u0026FIELDS%5BPROPERTY_151%5D=%D0%98%D0%9D%D0%9D+7730060164+%D0%9F%D0%A0%D0%98%D0%92%D0%9E%D0%9B%D0%96%D0%A1%D0%9A%D0%98%D0%99+%D0%A4%D0%98%D0%9B%D0%98%D0%90%D0%9B+%D0%9F%D0%90%D0%9E+%D0%A0%D0%9E%D0%A1%D0%91%D0%90%D0%9D%D0%9A\u0026FIELDS%5BPROPERTY_152%5D=8\u0026FIELDS%5BPROPERTY_153%5D=40702810524870001858\u0026FIELDS%5BPROPERTY_154%5D=%D0%9E%D0%9E%D0%9E+%22%D0%92%D0%AD%D0%A1%D0%A2%22%7E6+%D0%BF%D1%80%D0%B5%D0%B4%D0%BE%D1%81%D1%82%D0%B0%D0%B2%D0%BB%D0%B5%D0%BD%D0%B8%D0%B5+%D0%BA%D1%80%D0%B5%D0%B4%D0%B8%D1%82%D0%B0+%D0%94%D0%BE%D0%B3.MSW-R24-23-001054%2F05_19%2F03%2F2024\u0026FIELDS%5BPROPERTY_148%5D=3300000.00\u0026FIELDS%5BPROPERTY_160%5D=0\u0026FIELDS%5BPROPERTY_162%5D=25.03.2024\u0026FIELDS%5BPROPERTY_163%5D=60\u0026FIELDS%5BPROPERTY_166%5D=60\u0026FIELDS%5BPROPERTY_260%5D=CO_2393","26":"lists.element.add?IBLOCK_TYPE_ID=lists\u0026IBLOCK_ID=28\u0026ELEMENT_CODE=d4028cce8b5e272fde6b250c3c58889b\u0026FIELDS%5BNAME%5D=730\u0026FIELDS%5BPROPERTY_149%5D=730\u0026FIELDS%5BPROPERTY_146%5D=2024-03-20\u0026FIELDS%5BPROPERTY_147%5D=25000.00\u0026FIELDS%5BPROPERTY_150%5D=5836684401\u0026FIELDS%5BPROPERTY_151%5D=%D0%98%D0%9D%D0%9D+5836684401+%D0%9E%D0%9E%D0%9E+%22%D0%92%D0%AD%D0%A1%D0%A2%22\u0026FIELDS%5BPROPERTY_152%5D=8\u0026FIELDS%5BPROPERTY_153%5D=40702810524870001858\u0026FIELDS%5BPROPERTY_154%5D=%D0%9F%D0%B5%D1%80%D0%B5%D0%B2%D0%BE%D0%B4+%D1%81%D0%BE%D0%B1%D1%81%D1%82%D0%B2%D0%B5%D0%BD%D0%BD%D1%8B%D1%85+%D0%B4%D0%B5%D0%BD%D0%B5%D0%B6%D0%BD%D1%8B%D1%85+%D1%81%D1%80%D0%B5%D0%B4%D1%81%D1%82%D0%B2.+%D0%9D%D0%94%D0%A1+%D0%BD%D0%B5+%D0%BE%D0%B1%D0%BB%D0%B0%D0%B3%D0%B0%D0%B5%D1%82%D1%81%D1%8F.\u0026FIELDS%5BPROPERTY_148%5D=25000.00\u0026FIELDS%5BPROPERTY_160%5D=0\u0026FIELDS%5BPROPERTY_162%5D=25.03.2024\u0026FIELDS%5BPROPERTY_163%5D=60\u0026FIELDS%5BPROPERTY_166%5D=1\u0026FIELDS%5BPROPERTY_260%5D=CO_8","27":"lists.element.add?IBLOCK_TYPE_ID=lists\u0026IBLOCK_ID=28\u0026ELEMENT_CODE=75d2a690c6a414537c65fc5df13b2c97\u0026FIELDS%5BNAME%5D=727\u0026FIELDS%5BPROPERTY_149%5D=727\u0026FIELDS%5BPROPERTY_146%5D=2024-03-20\u0026FIELDS%5BPROPERTY_147%5D=175000.00\u0026FIELDS%5BPROPERTY_150%5D=5836684401\u0026FIELDS%5BPROPERTY_151%5D=%D0%98%D0%9D%D0%9D+5836684401+%D0%9E%D0%9E%D0%9E+%22%D0%92%D0%AD%D0%A1%D0%A2%22\u0026FIELDS%5BPROPERTY_152%5D=8\u0026FIELDS%5BPROPERTY_153%5D=40702810524870001858\u0026FIELDS%5BPROPERTY_154%5D=%D0%9F%D0%B5%D1%80%D0%B5%D0%B2%D0%BE%D0%B4+%D1%81%D0%BE%D0%B1%D1%81%D1%82%D0%B2%D0%B5%D0%BD%D0%BD%D1%8B%D1%85+%D0%B4%D0%B5%D0%BD%D0%B5%D0%B6%D0%BD%D1%8B%D1%85+%D1%81%D1%80%D0%B5%D0%B4%D1%81%D1%82%D0%B2.+%D0%9D%D0%94%D0%A1+%D0%BD%D0%B5+%D0%BE%D0%B1%D0%BB%D0%B0%D0%B3%D0%B0%D0%B5%D1%82%D1%81%D1%8F.\u0026FIELDS%5BPROPERTY_148%5D=175000.00\u0026FIELDS%5BPROPERTY_160%5D=0\u0026FIELDS%5BPROPERTY_162%5D=25.03.2024\u0026FIELDS%5BPROPERTY_163%5D=60\u0026FIELDS%5BPROPERTY_166%5D=1\u0026FIELDS%5BPROPERTY_260%5D=CO_8","28":"lists.element.add?IBLOCK_TYPE_ID=lists\u0026IBLOCK_ID=28\u0026ELEMENT_CODE=76ccd0e1945f08a7cd44bad2312ca9ce\u0026FIELDS%5BNAME%5D=230833\u0026FIELDS%5BPROPERTY_149%5D=230833\u0026FIELDS%5BPROPERTY_146%5D=2024-03-20\u0026FIELDS%5BPROPERTY_147%5D=500000.00\u0026FIELDS%5BPROPERTY_150%5D=7730060164\u0026FIELDS%5BPROPERTY_151%5D=%D0%98%D0%9D%D0%9D+7730060164+%D0%9F%D0%A0%D0%98%D0%92%D0%9E%D0%9B%D0%96%D0%A1%D0%9A%D0%98%D0%99+%D0%A4%D0%98%D0%9B%D0%98%D0%90%D0%9B+%D0%9F%D0%90%D0%9E+%D0%A0%D0%9E%D0%A1%D0%91%D0%90%D0%9D%D0%9A\u0026FIELDS%5BPROPERTY_152%5D=8\u0026FIELDS%5BPROPERTY_153%5D=40702810524870001858\u0026FIELDS%5BPROPERTY_154%5D=%D0%9E%D0%9E%D0%9E+%22%D0%92%D0%AD%D0%A1%D0%A2%22%7E6+%D0%BF%D1%80%D0%B5%D0%B4%D0%BE%D1%81%D1%82%D0%B0%D0%B2%D0%BB%D0%B5%D0%BD%D0%B8%D0%B5+%D0%BA%D1%80%D0%B5%D0%B4%D0%B8%D1%82%D0%B0+%D0%94%D0%BE%D0%B3.MSW-R24-23-001054%2F07_20%2F03%2F2024\u0026FIELDS%5BPROPERTY_148%5D=500000.00\u0026FIELDS%5BPROPERTY_160%5D=0\u0026FIELDS%5BPROPERTY_162%5D=25.03.2024\u0026FIELDS%5BPROPERTY_163%5D=60\u0026FIELDS%5BPROPERTY_166%5D=60\u0026FIELDS%5BPROPERTY_260%5D=CO_2393","33":"lists.element.add?IBLOCK_TYPE_ID=lists\u0026IBLOCK_ID=28\u0026ELEMENT_CODE=63d48ece6f46c9a8fee9a193969ade5c\u0026FIELDS%5BNAME%5D=198203\u0026FIELDS%5BPROPERTY_149%5D=198203\u0026FIELDS%5BPROPERTY_146%5D=2024-03-21\u0026FIELDS%5BPROPERTY_147%5D=350000.00\u0026FIELDS%5BPROPERTY_150%5D=7730060164\u0026FIELDS%5BPROPERTY_151%5D=%D0%98%D0%9D%D0%9D+7730060164+%D0%9F%D0%A0%D0%98%D0%92%D0%9E%D0%9B%D0%96%D0%A1%D0%9A%D0%98%D0%99+%D0%A4%D0%98%D0%9B%D0%98%D0%90%D0%9B+%D0%9F%D0%90%D0%9E+%D0%A0%D0%9E%D0%A1%D0%91%D0%90%D0%9D%D0%9A\u0026FIELDS%5BPROPERTY_152%5D=8\u0026FIELDS%5BPROPERTY_153%5D=40702810524870001858\u0026FIELDS%5BPROPERTY_154%5D=%D0%9E%D0%9E%D0%9E+%22%D0%92%D0%AD%D0%A1%D0%A2%22%7E6+%D0%BF%D1%80%D0%B5%D0%B4%D0%BE%D1%81%D1%82%D0%B0%D0%B2%D0%BB%D0%B5%D0%BD%D0%B8%D0%B5+%D0%BA%D1%80%D0%B5%D0%B4%D0%B8%D1%82%D0%B0+%D0%94%D0%BE%D0%B3.MSW-R24-23-001054%2F08_21%2F03%2F2024\u0026FIELDS%5BPROPERTY_148%5D=350000.00\u0026FIELDS%5BPROPERTY_160%5D=0\u0026FIELDS%5BPROPERTY_162%5D=25.03.2024\u0026FIELDS%5BPROPERTY_163%5D=60\u0026FIELDS%5BPROPERTY_166%5D=60\u0026FIELDS%5BPROPERTY_260%5D=CO_2393","74":"lists.element.add?IBLOCK_TYPE_ID=lists\u0026IBLOCK_ID=28\u0026ELEMENT_CODE=0069e9dfb084b8a0e29d338018838749\u0026FIELDS%5BNAME%5D=743\u0026FIELDS%5BPROPERTY_149%5D=743\u0026FIELDS%5BPROPERTY_146%5D=2024-03-22\u0026FIELDS%5BPROPERTY_147%5D=2500000.00\u0026FIELDS%5BPROPERTY_150%5D=5836684401\u0026FIELDS%5BPROPERTY_151%5D=%D0%98%D0%9D%D0%9D+5836684401+%D0%9E%D0%9E%D0%9E+%22%D0%92%D0%AD%D0%A1%D0%A2%22\u0026FIELDS%5BPROPERTY_152%5D=8\u0026FIELDS%5BPROPERTY_153%5D=40702810524870001858\u0026FIELDS%5BPROPERTY_154%5D=%D0%9F%D0%B5%D1%80%D0%B5%D0%B2%D0%BE%D0%B4+%D1%81%D0%BE%D0%B1%D1%81%D1%82%D0%B2%D0%B5%D0%BD%D0%BD%D1%8B%D1%85+%D0%B4%D0%B5%D0%BD%D0%B5%D0%B6%D0%BD%D1%8B%D1%85+%D1%81%D1%80%D0%B5%D0%B4%D1%81%D1%82%D0%B2.+%D0%9D%D0%94%D0%A1+%D0%BD%D0%B5+%D0%BE%D0%B1%D0%BB%D0%B0%D0%B3%D0%B0%D0%B5%D1%82%D1%81%D1%8F.\u0026FIELDS%5BPROPERTY_148%5D=2500000.00\u0026FIELDS%5BPROPERTY_160%5D=0\u0026FIELDS%5BPROPERTY_162%5D=25.03.2024\u0026FIELDS%5BPROPERTY_163%5D=60\u0026FIELDS%5BPROPERTY_166%5D=1\u0026FIELDS%5BPROPERTY_260%5D=CO_8"},"halt":0,"auth":"d93a0166005868f4005843ea000001e7000007b0c9ffaab6d74837f60b7234e5ab8141"}},"result":{"result":{"result":{"26":2814977,"27":2814978,"33":2814979,"74":2814980},"result_error":{"15":{"error":"ERROR_ELEMENT_ALREADY_EXISTS","error_description":"Element already exists"},"18":{"error":"ERROR_ELEMENT_ALREADY_EXISTS","error_description":"Element already exists"},"19":{"error":"ERROR_ELEMENT_ALREADY_EXISTS","error_description":"Element already exists"},"28":{"error":"ERROR_ELEMENT_ALREADY_EXISTS","error_description":"Element already exists"}},"result_total":[],"result_next":[],"result_time":{"26":{"start":1711353985.972427,"finish":1711353986.336466,"duration":0.36403918266296387,"processing":0.36398911476135254,"date_start":"2024-03-25T11:06:25+03:00","date_finish":"2024-03-25T11:06:26+03:00"},"27":{"start":1711353986.336648,"finish":1711353986.40934,"duration":0.0726919174194336,"processing":0.0726161003112793,"date_start":"2024-03-25T11:06:26+03:00","date_finish":"2024-03-25T11:06:26+03:00"},"33":{"start":1711353986.411474,"finish":1711353986.469404,"duration":0.05792999267578125,"processing":0.057868003845214844,"date_start":"2024-03-25T11:06:26+03:00","date_finish":"2024-03-25T11:06:26+03:00"},"74":{"start":1711353986.469572,"finish":1711353986.564893,"duration":0.0953209400177002,"processing":0.0952451229095459,"date_start":"2024-03-25T11:06:26+03:00","date_finish":"2024-03-25T11:06:26+03:00"}}},"time":{"start":1711353985.260548,"finish":1711353986.564921,"duration":1.304372787475586,"processing":0.6064610481262207,"date_start":"2024-03-25T11:06:25+03:00","date_finish":"2024-03-25T11:06:26+03:00"}}}