{"url":"https:\/\/dev.vestrus.ru\/rest\/imbot.bot.list.json","info":{"url":"https:\/\/dev.vestrus.ru\/rest\/imbot.bot.list.json","content_type":"application\/json; charset=utf-8","http_code":200,"header_size":765,"request_size":182,"filetime":-1,"ssl_verify_result":0,"redirect_count":0,"total_time":0.396409,"namelookup_time":0.000421,"connect_time":0.023388,"pretransfer_time":0.086441,"size_upload":75,"size_download":670,"speed_download":1691,"speed_upload":189,"download_content_length":670,"upload_content_length":75,"starttransfer_time":0.086839,"redirect_time":0,"redirect_url":"","primary_ip":"94.181.180.218","certinfo":[],"primary_port":443,"local_ip":"37.140.192.240","local_port":49268,"http_version":3,"protocol":2,"ssl_verifyresult":0,"scheme":"HTTPS","appconnect_time_us":84844,"connect_time_us":23388,"namelookup_time_us":421,"pretransfer_time_us":86441,"redirect_time_us":0,"starttransfer_time_us":86839,"total_time_us":396409},"params":{"method":"imbot.bot.list","params":{"auth":"1cd47e66006e8580005843ea00000321000007f2db447a1bddda0a417f9844a80616fe"}},"result":{"result":{"802":{"ID":802,"NAME":"\u0411\u043e\u0442 5 \u0431\u0443\u043a\u0432","CODE":"skyweb24.5letter","OPENLINE":"Y"},"804":{"ID":804,"NAME":"TestBot","CODE":"TestBot","OPENLINE":"N"},"805":{"ID":805,"NAME":"\u042e\u043d\u0438\u0412\u042d\u0421\u0422","CODE":"unixbot_01","OPENLINE":"Y"},"879":{"ID":879,"NAME":"\u041d\u0438\u043a\u043e\u043b\u0430\u0439 \u041d\u0438\u043a\u043e\u043b\u0430\u0435\u0432\u0438\u0447","CODE":"helloworldbot","OPENLINE":"N"}},"time":{"start":1719584273.35567,"finish":1719584273.59356,"duration":0.23789000511169434,"processing":0.03365302085876465,"date_start":"2024-06-28T17:17:53+03:00","date_finish":"2024-06-28T17:17:53+03:00"}}}